Workbook

Sheet Orders
A1: Order_ID | B1: Order_Date | C1: Customer_ID | D1: Category | E1: Sales | F1: Profit | G1: Discount | H1: Region | I1: Segment
A2: ORD-1001 | B2: 45662 | C2: C001 | D2: Technology | E2: 1250 | F2: 250 | G2: 0 | H2: =INDEX(Customers!C:C, MATCH(C2, Customers!A:A, 0)) -> West | I2: =INDEX(Customers!D:D, MATCH(C2, Customers!A:A, 0)) -> Consumer | Q2: Region | R2: Total Sales | S2: Total Profit | T2: Progit Margin
A3: ORD-1002 | B3: 45669 | C3: C006 | D3: Office Supplies | E3: 120.5 | F3: 30.1 | G3: 0 | H3: =INDEX(Customers!C:C, MATCH(C3, Customers!A:A, 0)) -> East | I3: =INDEX(Customers!D:D, MATCH(C3, Customers!A:A, 0)) -> Consumer | J3: Years (Order_Date) | K3: Months (Order_Date) | L3: Sum of Sales | M3: Previous Month Sales | N3: Variance | O3: Growth% | Q3: North | R3: =SUMIFS(E:E, H:H, Q3) -> 19475 | S3: =SUMIFS(F:F, H:H, Q3) -> 3583.25 | T3: =IF(R3=0, 0, S3/R3) -> 0.1839923
A4: ORD-1003 | B4: 45675 | C4: C011 | D4: Furniture | E4: 850 | F4: 85 | G4: 0.1 | H4: =INDEX(Customers!C:C, MATCH(C4, Customers!A:A, 0)) -> North | I4: =INDEX(Customers!D:D, MATCH(C4, Customers!A:A, 0)) -> Consumer | J4: 2025 | K4: Jan | L4: 2735.5 | Q4: South | R4: =SUMIFS(E:E, H:H, Q4) -> 11150 | S4: =SUMIFS(F:F, H:H, Q4) -> -1916.5 | T4: =IF(R4=0, 0, S4/R4) -> -0.17188341
A5: ORD-1004 | B5: 45679 | C5: C016 | D5: Technology | E5: 450 | F5: -45 | G5: 0.3 | H5: =INDEX(Customers!C:C, MATCH(C5, Customers!A:A, 0)) -> South | I5: =INDEX(Customers!D:D, MATCH(C5, Customers!A:A, 0)) -> Consumer | K5: Feb | L5: 3435 | M5: =L4 -> 2735.5 | N5: =L5-M5 -> 699.5 | O5: =IFERROR(N5/M5, 0) -> 0.25571194 | Q5: East | R5: =SUMIFS(E:E, H:H, Q5) -> 24740.5 | S5: =SUMIFS(F:F, H:H, Q5) -> 5402.6 | T5: =IF(R5=0, 0, S5/R5) -> 0.21837069
A6: ORD-1005 | B6: 45685 | C6: C002 | D6: Office Supplies | E6: 65 | F6: 15 | G6: 0 | H6: =INDEX(Customers!C:C, MATCH(C6, Customers!A:A, 0)) -> West | I6: =INDEX(Customers!D:D, MATCH(C6, Customers!A:A, 0)) -> Corporate | K6: Mar | L6: 4930 | M6: =L5 -> 3435 | N6: =L6-M6 -> 1495 | O6: =IFERROR(N6/M6, 0) -> 0.43522562 | Q6: West | R6: =SUMIFS(E:E, H:H, Q6) -> 20320 | S6: =SUMIFS(F:F, H:H, Q6) -> 4307.75 | T6: =IF(R6=0, 0, S6/R6) -> 0.21199557
A7: ORD-1006 | B7: 45691 | C7: C007 | D7: Technology | E7: 1500 | F7: 375 | G7: 0.05 | H7: =INDEX(Customers!C:C, MATCH(C7, Customers!A:A, 0)) -> East | I7: =INDEX(Customers!D:D, MATCH(C7, Customers!A:A, 0)) -> Corporate | K7: Apr | L7: 3350 | M7: =L6 -> 4930 | N7: =L7-M7 -> -1580 | O7: =IFERROR(N7/M7, 0) -> -0.32048682
A8: ORD-1007 | B8: 45697 | C8: C012 | D8: Furniture | E8: 920 | F8: 46 | G8: 0.15 | H8: =INDEX(Customers!C:C, MATCH(C8, Customers!A:A, 0)) -> North | I8: =INDEX(Customers!D:D, MATCH(C8, Customers!A:A, 0)) -> Corporate | K8: May | L8: 3475 | M8: =L7 -> 3350 | N8: =L8-M8 -> 125 | O8: =IFERROR(N8/M8, 0) -> 0.037313433
A9: ORD-1008 | B9: 45702 | C9: C017 | D9: Office Supplies | E9: 310 | F9: -31 | G9: 0.25 | H9: =INDEX(Customers!C:C, MATCH(C9, Customers!A:A, 0)) -> South | I9: =INDEX(Customers!D:D, MATCH(C9, Customers!A:A, 0)) -> Corporate | K9: Jun | L9: 4045 | M9: =L8 -> 3475 | N9: =L9-M9 -> 570 | O9: =IFERROR(N9/M9, 0) -> 0.16402878 | Q9: Segment | R9: Revenue | S9: Contribution%
A10: ORD-1009 | B10: 45707 | C10: C003 | D10: Technology | E10: 620 | F10: 124 | G10: 0.1 | H10: =INDEX(Customers!C:C, MATCH(C10, Customers!A:A, 0)) -> West | I10: =INDEX(Customers!D:D, MATCH(C10, Customers!A:A, 0)) -> Home Office | K10: Jul | L10: 3820 | M10: =L9 -> 4045 | N10: =L10-M10 -> -225 | O10: =IFERROR(N10/M10, 0) -> -0.055624227 | Q10: Consumer | R10: =SUMIFS(E:E, I:I, Q10) -> 29745.5 | S10: =R10/SUM($R$10:$R$12) -> 0.39301451
A11: ORD-1010 | B11: 45713 | C11: C008 | D11: Office Supplies | E11: 85 | F11: 21.25 | G11: 0 | H11: =INDEX(Customers!C:C, MATCH(C11, Customers!A:A, 0)) -> East | I11: =INDEX(Customers!D:D, MATCH(C11, Customers!A:A, 0)) -> Home Office | K11: Aug | L11: 3425 | M11: =L10 -> 3820 | N11: =L11-M11 -> -395 | O11: =IFERROR(N11/M11, 0) -> -0.10340314 | Q11: Corporate | R11: =SUMIFS(E:E, I:I, Q11) -> 31530 | S11: =R11/SUM($R$10:$R$12) -> 0.41659235
A12: ORD-1011 | B12: 45718 | C12: C013 | D12: Furniture | E12: 1100 | F12: 165 | G12: 0.05 | H12: =INDEX(Customers!C:C, MATCH(C12, Customers!A:A, 0)) -> North | I12: =INDEX(Customers!D:D, MATCH(C12, Customers!A:A, 0)) -> Home Office | K12: Sep | L12: 3195 | M12: =L11 -> 3425 | N12: =L12-M12 -> -230 | O12: =IFERROR(N12/M12, 0) -> -0.067153285 | Q12: Home Office | R12: =SUMIFS(E:E, I:I, Q12) -> 14410 | S12: =R12/SUM($R$10:$R$12) -> 0.19039314
A13: ORD-1012 | B13: 45724 | C13: C018 | D13: Technology | E13: 540 | F13: -108 | G13: 0.35 | H13: =INDEX(Customers!C:C, MATCH(C13, Customers!A:A, 0)) -> South | I13: =INDEX(Customers!D:D, MATCH(C13, Customers!A:A, 0)) -> Home Office | K13: Oct | L13: 4520 | M13: =L12 -> 3195 | N13: =L13-M13 -> 1325 | O13: =IFERROR(N13/M13, 0) -> 0.41471049
A14: ORD-1013 | B14: 45731 | C14: C004 | D14: Office Supplies | E14: 430 | F14: 86 | G14: 0.1 | H14: =INDEX(Customers!C:C, MATCH(C14, Customers!A:A, 0)) -> West | I14: =INDEX(Customers!D:D, MATCH(C14, Customers!A:A, 0)) -> Consumer | K14: Nov | L14: 3830 | M14: =L13 -> 4520 | N14: =L14-M14 -> -690 | O14: =IFERROR(N14/M14, 0) -> -0.15265487
A15: ORD-1014 | B15: 45737 | C15: C009 | D15: Technology | E15: 2100 | F15: 525 | G15: 0 | H15: =INDEX(Customers!C:C, MATCH(C15, Customers!A:A, 0)) -> East | I15: =INDEX(Customers!D:D, MATCH(C15, Customers!A:A, 0)) -> Consumer | K15: Dec | L15: 3735 | M15: =L14 -> 3830 | N15: =L15-M15 -> -95 | O15: =IFERROR(N15/M15, 0) -> -0.024804178
A16: ORD-1015 | B16: 45743 | C16: C014 | D16: Furniture | E16: 760 | F16: 76 | G16: 0.1 | H16: =INDEX(Customers!C:C, MATCH(C16, Customers!A:A, 0)) -> North | I16: =INDEX(Customers!D:D, MATCH(C16, Customers!A:A, 0)) -> Consumer | J16: 2026 | K16: Jan | L16: 3890 | M16: =L15 -> 3735 | N16: =L16-M16 -> 155 | O16: =IFERROR(N16/M16, 0) -> 0.041499331 | Q16: Sum of Sales | R16: Column Labels
A17: ORD-1016 | B17: 45751 | C17: C019 | D17: Office Supplies | E17: 190 | F17: -19 | G17: 0.3 | H17: =INDEX(Customers!C:C, MATCH(C17, Customers!A:A, 0)) -> South | I17: =INDEX(Customers!D:D, MATCH(C17, Customers!A:A, 0)) -> Consumer | K17: Feb | L17: 3490 | M17: =L16 -> 3890 | N17: =L17-M17 -> -400 | O17: =IFERROR(N17/M17, 0) -> -0.10282776 | Q17: Row Labels | R17: 2025 | S17: 2026 | T17: Grand Total | W17: Category | X17: 2025 Sales | Y17: 2026 Sales | Z17: Growth%
A18: ORD-1017 | B18: 45757 | C18: C005 | D18: Technology | E18: 890 | F18: 178 | G18: 0.05 | H18: =INDEX(Customers!C:C, MATCH(C18, Customers!A:A, 0)) -> West | I18: =INDEX(Customers!D:D, MATCH(C18, Customers!A:A, 0)) -> Corporate | K18: Mar | L18: 4530 | M18: =L17 -> 3490 | N18: =L18-M18 -> 1040 | O18: =IFERROR(N18/M18, 0) -> 0.29799427 | Q18: Furniture | R18: 15300 | S18: 9810 | T18: 25110 | W18: Furniture | X18: 15300 | Y18: 9810 | Z18: =(Y18 - X18) / X18 -> -0.35882353
A19: ORD-1018 | B19: 45763 | C19: C010 | D19: Furniture | E19: 1350 | F19: 202.5 | G19: 0 | H19: =INDEX(Customers!C:C, MATCH(C19, Customers!A:A, 0)) -> East | I19: =INDEX(Customers!D:D, MATCH(C19, Customers!A:A, 0)) -> Corporate | K19: Apr | L19: 3410 | M19: =L18 -> 4530 | N19: =L19-M19 -> -1120 | O19: =IFERROR(N19/M19, 0) -> -0.24724062 | Q19: Office Supplies | R19: 4675.5 | S19: 3200 | T19: 7875.5 | W19: Office Supplies | X19: 4675.5 | Y19: 3200 | Z19: =(Y19 - X19) / X19 -> -0.31558122
A20: ORD-1019 | B20: 45769 | C20: C015 | D20: Office Supplies | E20: 250 | F20: 50 | G20: 0.1 | H20: =INDEX(Customers!C:C, MATCH(C20, Customers!A:A, 0)) -> North | I20: =INDEX(Customers!D:D, MATCH(C20, Customers!A:A, 0)) -> Corporate | K20: May | L20: 4370 | M20: =L19 -> 3410 | N20: =L20-M20 -> 960 | O20: =IFERROR(N20/M20, 0) -> 0.28152493 | Q20: Technology | R20: 24520 | S20: 18180 | T20: 42700 | W20: Technology | X20: 24520 | Y20: 18180 | Z20: =(Y20 - X20) / X20 -> -0.25856444
A21: ORD-1020 | B21: 45775 | C21: C020 | D21: Technology | E21: 670 | F21: -134 | G21: 0.4 | H21: =INDEX(Customers!C:C, MATCH(C21, Customers!A:A, 0)) -> South | I21: =INDEX(Customers!D:D, MATCH(C21, Customers!A:A, 0)) -> Corporate | K21: Jun | L21: 2940 | M21: =L20 -> 4370 | N21: =L21-M21 -> -1430 | O21: =IFERROR(N21/M21, 0) -> -0.32723112 | Q21: Grand Total | R21: 44495.5 | S21: 31190 | T21: 75685.5
A22: ORD-1021 | B22: 45780 | C22: C001 | D22: Furniture | E22: 510 | F22: 51 | G22: 0.1 | H22: =INDEX(Customers!C:C, MATCH(C22, Customers!A:A, 0)) -> West | I22: =INDEX(Customers!D:D, MATCH(C22, Customers!A:A, 0)) -> Consumer | K22: Jul | L22: 5030 | M22: =L21 -> 2940 | N22: =L22-M22 -> 2090 | O22: =IFERROR(N22/M22, 0) -> 0.71088435
A23: ORD-1022 | B23: 45786 | C23: C006 | D23: Technology | E23: 1420 | F23: 355 | G23: 0 | H23: =INDEX(Customers!C:C, MATCH(C23, Customers!A:A, 0)) -> East | I23: =INDEX(Customers!D:D, MATCH(C23, Customers!A:A, 0)) -> Consumer | K23: Aug | L23: 3530 | M23: =L22 -> 5030 | N23: =L23-M23 -> -1500 | O23: =IFERROR(N23/M23, 0) -> -0.29821074
A24: ORD-1023 | B24: 45792 | C24: C011 | D24: Office Supplies | E24: 115 | F24: 28.75 | G24: 0 | H24: =INDEX(Customers!C:C, MATCH(C24, Customers!A:A, 0)) -> North | I24: =INDEX(Customers!D:D, MATCH(C24, Customers!A:A, 0)) -> Consumer | J24: Grand Total | L24: 75685.5
A25: ORD-1024 | B25: 45797 | C25: C016 | D25: Furniture | E25: 480 | F25: -72 | G25: 0.3 | H25: =INDEX(Customers!C:C, MATCH(C25, Customers!A:A, 0)) -> South | I25: =INDEX(Customers!D:D, MATCH(C25, Customers!A:A, 0)) -> Consumer
A26: ORD-1025 | B26: 45803 | C26: C002 | D26: Technology | E26: 950 | F26: 190 | G26: 0.1 | H26: =INDEX(Customers!C:C, MATCH(C26, Customers!A:A, 0)) -> West | I26: =INDEX(Customers!D:D, MATCH(C26, Customers!A:A, 0)) -> Corporate
A27: ORD-1026 | B27: 45809 | C27: C007 | D27: Office Supplies | E27: 340 | F27: 68 | G27: 0.1 | H27: =INDEX(Customers!C:C, MATCH(C27, Customers!A:A, 0)) -> East | I27: =INDEX(Customers!D:D, MATCH(C27, Customers!A:A, 0)) -> Corporate
A28: ORD-1027 | B28: 45815 | C28: C012 | D28: Technology | E28: 1800 | F28: 450 | G28: 0.05 | H28: =INDEX(Customers!C:C, MATCH(C28, Customers!A:A, 0)) -> North | I28: =INDEX(Customers!D:D, MATCH(C28, Customers!A:A, 0)) -> Corporate
A29: ORD-1028 | B29: 45820 | C29: C017 | D29: Furniture | E29: 610 | F29: -61 | G29: 0.25 | H29: =INDEX(Customers!C:C, MATCH(C29, Customers!A:A, 0)) -> South | I29: =INDEX(Customers!D:D, MATCH(C29, Customers!A:A, 0)) -> Corporate
A30: ORD-1029 | B30: 45826 | C30: C003 | D30: Office Supplies | E30: 145 | F30: 36.25 | G30: 0 | H30: =INDEX(Customers!C:C, MATCH(C30, Customers!A:A, 0)) -> West | I30: =INDEX(Customers!D:D, MATCH(C30, Customers!A:A, 0)) -> Home Office
A31: ORD-1030 | B31: 45832 | C31: C008 | D31: Technology | E31: 1150 | F31: 230 | G31: 0.1 | H31: =INDEX(Customers!C:C, MATCH(C31, Customers!A:A, 0)) -> East | I31: =INDEX(Customers!D:D, MATCH(C31, Customers!A:A, 0)) -> Home Office
A32: ORD-1031 | B32: 45840 | C32: C013 | D32: Furniture | E32: 890 | F32: 133.5 | G32: 0.05 | H32: =INDEX(Customers!C:C, MATCH(C32, Customers!A:A, 0)) -> North | I32: =INDEX(Customers!D:D, MATCH(C32, Customers!A:A, 0)) -> Home Office
A33: ORD-1032 | B33: 45846 | C33: C018 | D33: Office Supplies | E33: 210 | F33: -42 | G33: 0.35 | H33: =INDEX(Customers!C:C, MATCH(C33, Customers!A:A, 0)) -> South | I33: =INDEX(Customers!D:D, MATCH(C33, Customers!A:A, 0)) -> Home Office
A34: ORD-1033 | B34: 45852 | C34: C004 | D34: Technology | E34: 730 | F34: 146 | G34: 0.1 | H34: =INDEX(Customers!C:C, MATCH(C34, Customers!A:A, 0)) -> West | I34: =INDEX(Customers!D:D, MATCH(C34, Customers!A:A, 0)) -> Consumer
A35: ORD-1034 | B35: 45858 | C35: C009 | D35: Furniture | E35: 1600 | F35: 320 | G35: 0 | H35: =INDEX(Customers!C:C, MATCH(C35, Customers!A:A, 0)) -> East | I35: =INDEX(Customers!D:D, MATCH(C35, Customers!A:A, 0)) -> Consumer
A36: ORD-1035 | B36: 45864 | C36: C014 | D36: Office Supplies | E36: 390 | F36: 78 | G36: 0.1 | H36: =INDEX(Customers!C:C, MATCH(C36, Customers!A:A, 0)) -> North | I36: =INDEX(Customers!D:D, MATCH(C36, Customers!A:A, 0)) -> Consumer
... A101: ORD-1100 | B101: 46259 | C101: C020 | D101: Technology | E101: 600 | F101: -120 | G101: 0.4 | H101: =INDEX(Customers!C:C, MATCH(C101, Customers!A:A, 0)) -> South | I101: =INDEX(Customers!D:D, MATCH(C101, Customers!A:A, 0)) -> Corporate

Sheet Customers
A1: Customer_ID | B1: Customer_Name | C1: Region | D1: Segment
A2: C001 | B2: Aarav Sharma | C2: West | D2: Consumer
A3: C002 | B3: Diya Patel | C3: West | D3: Corporate
A4: C003 | B4: John Gupta | C4: West | D4: Home Office
A5: C004 | B5: Priya Nair | C5: West | D5: Consumer
A6: C005 | B6: Rohan Mehta | C6: West | D6: Corporate
A7: C006 | B7: Ananya Rao | C7: East | D7: Consumer
A8: C007 | B8: Vikram Singh | C8: East | D8: Corporate
A9: C008 | B9: Sanya Verma | C9: East | D9: Home Office
A10: C009 | B10: Kabir Das | C10: East | D10: Consumer
A11: C010 | B11: Meera Joshi | C11: East | D11: Corporate
A12: C011 | B12: Arjun Kumar | C12: North | D12: Consumer
... A21: C020 | B21: Simran Kaur | C21: South | D21: Corporate
